youtube_bulk_upload/__init__.py
youtube_bulk_upload/__init__.pyi
youtube_bulk_upload/bulk_upload.py
youtube_bulk_upload/bulk_upload.pyi
youtube_bulk_upload/cli.py
youtube_bulk_upload/gui.py
youtube_bulk_upload/logo.ico
youtube_bulk_upload/logo.png
youtube_bulk_upload-0.5.5.dist-info/LICENSE
youtube_bulk_upload-0.5.5.dist-info/METADATA
youtube_bulk_upload-0.5.5.dist-info/WHEEL
youtube_bulk_upload-0.5.5.dist-info/entry_points.txt
youtube_bulk_upload-0.5.5.dist-info/RECORD
